align_track/__init__.py
align_track/list_runs.py
align_track/py.typed
align_track-1.5.0.dist-info/METADATA
align_track-1.5.0.dist-info/WHEEL
align_track-1.5.0.dist-info/entry_points.txt
align_track-1.5.0.dist-info/RECORD
